{"openapi":"3.0.2","info":{"title":"FastAPI","version":"0.1.0"},"paths":{"/event":{"get":{"summary":"Get Event","operationId":"get_event_event_get","responses":{"200":{"description":"Successful Response","content":{"application/json":{"schema":{"title":"Response Get Event Event Get","type":"array","items":{"$ref":"#/components/schemas/Event"}}}}}}},"post":{"summary":"Create Event","operationId":"create_event_event_post","requestBody":{"content":{"application/json":{"schema":{"$ref":"#/components/schemas/Event"}}},"required":true},"responses":{"200":{"description":"Successful Response","content":{"application/json":{"schema":{"title":"Response Create Event Event Post","type":"object"}}}},"422":{"description":"Validation Error","content":{"application/json":{"schema":{"$ref":"#/components/schemas/HTTPValidationError"}}}}}}},"/image":{"post":{"summary":"Create Picture","description":"Takes image file, returns url to IPFS Storage","operationId":"create_picture_image_post","requestBody":{"content":{"multipart/form-data":{"schema":{"$ref":"#/components/schemas/Body_create_picture_image_post"}}},"required":true},"responses":{"200":{"description":"Successful Response","content":{"application/json":{"schema":{"title":"Response Create Picture Image Post","type":"string"}}}},"422":{"description":"Validation Error","content":{"application/json":{"schema":{"$ref":"#/components/schemas/HTTPValidationError"}}}}}}},"/account":{"post":{"summary":"Crete Account","operationId":"crete_account_account_post","requestBody":{"content":{"application/json":{"schema":{"$ref":"#/components/schemas/User"}}},"required":true},"responses":{"200":{"description":"Successful Response","content":{"application/json":{"schema":{"$ref":"#/components/schemas/LoginResponse"}}}},"422":{"description":"Validation Error","content":{"application/json":{"schema":{"$ref":"#/components/schemas/HTTPValidationError"}}}}}}},"/login":{"post":{"summary":"Log To Account","operationId":"log_to_account_login_post","parameters":[{"required":true,"schema":{"title":"User Email","type":"string"},"name":"user_email","in":"query"},{"required":true,"schema":{"title":"User Password","type":"string"},"name":"user_password","in":"query"}],"responses":{"200":{"description":"Successful Response","content":{"application/json":{"schema":{"$ref":"#/components/schemas/LoginResponse"}}}},"422":{"description":"Validation Error","content":{"application/json":{"schema":{"$ref":"#/components/schemas/HTTPValidationError"}}}}}}},"/":{"get":{"summary":"Root","operationId":"root__get","responses":{"200":{"description":"Successful Response","content":{"application/json":{"schema":{}}}}}}}},"components":{"schemas":{"Body_create_picture_image_post":{"title":"Body_create_picture_image_post","required":["second_art"],"type":"object","properties":{"second_art":{"title":"Second Art","type":"string","format":"binary"}}},"Event":{"title":"Event","required":["name","description","start_day","finish_day","event_image","preview_image","contract_address","ticket_quantity","ticket_price"],"type":"object","properties":{"name":{"title":"Name","type":"string"},"description":{"title":"Description","type":"string"},"start_day":{"title":"Start Day","type":"string"},"finish_day":{"title":"Finish Day","type":"string"},"event_image":{"title":"Event Image","type":"string"},"preview_image":{"title":"Preview Image","type":"string"},"contract_address":{"title":"Contract Address","type":"string"},"ticket_quantity":{"title":"Ticket Quantity","type":"integer"},"ticket_price":{"title":"Ticket Price","type":"number"}}},"HTTPValidationError":{"title":"HTTPValidationError","type":"object","properties":{"detail":{"title":"Detail","type":"array","items":{"$ref":"#/components/schemas/ValidationError"}}}},"LoginResponse":{"title":"LoginResponse","required":["accessToken"],"type":"object","properties":{"accessToken":{"title":"Accesstoken","type":"string"}}},"User":{"title":"User","required":["user_email","user_name","user_password"],"type":"object","properties":{"user_email":{"title":"User Email","type":"string"},"user_name":{"title":"User Name","type":"string"},"user_password":{"title":"User Password","type":"string"}}},"ValidationError":{"title":"ValidationError","required":["loc","msg","type"],"type":"object","properties":{"loc":{"title":"Location","type":"array","items":{"anyOf":[{"type":"string"},{"type":"integer"}]}},"msg":{"title":"Message","type":"string"},"type":{"title":"Error Type","type":"string"}}}}}}